photos/__init__.py
photos/admin.py
photos/forms.py
photos/how_to.md
photos/managers.py
photos/models.py
photos/tests.py
photos/urls.py
photos/views.py
photos/fixtures/photos.json
photos/migrations/0001_initial.py
photos/migrations/__init__.py
photos/templates/galleries/base.html
photos/templates/galleries/gallery_detail.html
photos/templates/galleries/gallery_list.html
photos/templates/galleries/includes/related_galleries.html
photos/templates/photos/base.html
photos/templates/photos/gallery_detail.html
photos/templates/photos/gallery_list.html
photos/templates/photos/includes/related_galleries.html
photos/templatetags/__init__.py
photos/templatetags/gallery_tags.py
tango_photos-0.5.1.dist-info/METADATA
tango_photos-0.5.1.dist-info/RECORD
tango_photos-0.5.1.dist-info/WHEEL
tango_photos-0.5.1.dist-info/top_level.txt
