Metadata-Version: 1.0
Name: tango-photos
Version: 0.5.1
Summary: Reusable Django photo galleries app. Can be used with or without Tango.
Home-page: http://github.com/tBaxter/tango-photos
Author: Tim Baxter
Author-email: mail.baxter@gmail.com
License: LICENSE.txt
Platform: UNKNOWN
